sciltagger/__init__.py
sciltagger/config.py
sciltagger/getmodel.py
sciltagger/labelconvert.py
sciltagger/modeltest.py
sciltagger/pandm.py
sciltagger/tagger.py
sciltagger/test.py
pySCILTagger-0.0.4.dist-info/LICENSE
pySCILTagger-0.0.4.dist-info/METADATA
pySCILTagger-0.0.4.dist-info/WHEEL
pySCILTagger-0.0.4.dist-info/top_level.txt
pySCILTagger-0.0.4.dist-info/RECORD
