Metadata-Version: 2.1
Name: pySCILTagger
Version: 0.0.4
Summary: A dialog-act tagger for pySCIL.
Home-page: https://github.com/Malorn44/pySCIL-tagger
Author: Mara Schwartz, Jeremy Macks
Author-email: maraschwartz44@gmail.com, macksj@rpi.edu
Project-URL: Documentation, https://github.com/Malorn44/pySCIL-tagger
Project-URL: Source Code, https://github.com/Malorn44/pySCIL-tagger
Classifier: Programming Language :: Python :: 3
Classifier: License :: OSI Approved :: MIT License
Classifier: Operating System :: OS Independent
Requires-Python: >=3.6
License-File: LICENSE
